ecalc_cli/README.md
ecalc_cli/__init__.py
ecalc_cli/emission_intensity.py
ecalc_cli/errors.py
ecalc_cli/logger.py
ecalc_cli/main.py
ecalc_cli/types.py
ecalc_cli/commands/__init__.py
ecalc_cli/commands/run.py
ecalc_cli/commands/selftest.py
ecalc_cli/commands/show.py
ecalc_cli/infrastructure/file_resource_service.py
ecalc_cli/io/__init__.py
ecalc_cli/io/output.py
ecalc_neqsim_wrapper/README.md
ecalc_neqsim_wrapper/__init__.py
ecalc_neqsim_wrapper/cache_service.py
ecalc_neqsim_wrapper/components.py
ecalc_neqsim_wrapper/exceptions.py
ecalc_neqsim_wrapper/fluid_service.py
ecalc_neqsim_wrapper/java_service.py
ecalc_neqsim_wrapper/mappings.py
ecalc_neqsim_wrapper/thermo.py
ecalc_neqsim_wrapper/lib/NeqSim.jar
ecalc_neqsim_wrapper/lib/neqsim_version_info.md
libecalc/__init__.py
libecalc/version.py
libecalc/application/__init__.py
libecalc/application/common_stream_distribution.py
libecalc/application/priorities_stream_distribution.py
libecalc/application/stream_distribution.py
libecalc/common/__init__.py
libecalc/common/chart_type.py
libecalc/common/component_type.py
libecalc/common/consumption_type.py
libecalc/common/discriminator_fallback.py
libecalc/common/ecalc_base_model.py
libecalc/common/energy_usage_type.py
libecalc/common/fixed_speed_pressure_control.py
libecalc/common/graph.py
libecalc/common/interpolation.py
libecalc/common/logger.py
libecalc/common/priority_optimizer.py
libecalc/common/run_info.py
libecalc/common/temporal_model.py
libecalc/common/time_utils.py
libecalc/common/units.py
libecalc/common/variables.py
libecalc/common/version.py
libecalc/common/component_info/__init__.py
libecalc/common/component_info/component_level.py
libecalc/common/component_info/compressor.py
libecalc/common/datetime/__init__.py
libecalc/common/datetime/utils.py
libecalc/common/decorators/__init__.py
libecalc/common/decorators/capturer.py
libecalc/common/decorators/feature_flags.py
libecalc/common/errors/__init__.py
libecalc/common/errors/exceptions.py
libecalc-13.0.2.dist-info/METADATA
libecalc-13.0.2.dist-info/WHEEL
libecalc-13.0.2.dist-info/entry_points.txt
libecalc-13.0.2.dist-info/licenses/LICENSE
libecalc-13.0.2.dist-info/RECORD
