Metadata-Version: 2.4
Name: libecalc
Version: 13.0.2
Summary: eCalc™ is a software tool for calculation of energy demand and greenhouse gas (GHG) emissions from oil and gas production and processing.
Project-URL: Homepage, https://github.com/equinor/ecalc
Project-URL: Repository, https://github.com/equinor/ecalc
Author-email: eCalc Team <fg_ecalc@equinor.com>
License-Expression: LGPL-3.0-only
License-File: LICENSE
Keywords: emission,energy,engineering,scientific
Classifier: Development Status :: 5 - Production/Stable
Classifier: Intended Audience :: Science/Research
Classifier: License :: OSI Approved :: GNU Lesser General Public License v3 (LGPLv3)
Classifier: Natural Language :: English
Classifier: Operating System :: MacOS
Classifier: Operating System :: POSIX :: Linux
Classifier: Programming Language :: Python :: 3.11
Classifier: Programming Language :: Python :: 3.12
Classifier: Programming Language :: Python :: 3.13
Classifier: Topic :: Scientific/Engineering
Classifier: Topic :: Scientific/Engineering :: Physics
Classifier: Topic :: Software Development :: Libraries
Classifier: Topic :: Utilities
Requires-Python: <3.14,>=3.11
Requires-Dist: jneqsim>=3.0.42
Requires-Dist: networkx~=3.2
Requires-Dist: numpy<3
Requires-Dist: orjson~=3.8
Requires-Dist: pandas==2.*
Requires-Dist: py4j~=0.10
Requires-Dist: pydantic<3
Requires-Dist: pyyaml==6.*
Requires-Dist: rich==14.*
Requires-Dist: ruamel-yaml~=0.18
Requires-Dist: scipy<2
Requires-Dist: shapely==2.*
Requires-Dist: typer==0.*
